.testr.conf
AUTHORS
ChangeLog
LICENSE
README.md
requirements.txt
setup.cfg
setup.py
test-requirements.txt
tox.ini
crosshair/__init__.py
crosshair/commands.py
crosshair/plugins.py
crosshair/shell.py
crosshair/ssh.py
crosshair.egg-info/PKG-INFO
crosshair.egg-info/SOURCES.txt
crosshair.egg-info/dependency_links.txt
crosshair.egg-info/not-zip-safe
crosshair.egg-info/pbr.json
crosshair.egg-info/requires.txt
crosshair.egg-info/top_level.txt
tests/__init__.py
tests/test_command.py
tests/test_pluginmanager.py
tests/test_shell.py
tests/test_ssh.py
tests/data/host_key
tests/data/private_keys/admin
tests/data/private_keys/user
tests/data/public_keys/admin.pub
tests/data/public_keys/user.pub