Metadata-Version: 1.1
Name: crosshair
Version: 0.1.0.dev11
Summary: Issue commands to your application using SSH
Home-page: UNKNOWN
Author: Nicola Heald
Author-email: nicola@notnowlewis.com
License: UNKNOWN
Platform: UNKNOWN
Classifier: Intended Audience :: Developers
Classifier: License :: OSI Approved :: Apache Software License
Classifier: Operating System :: POSIX :: Linux
Classifier: Programming Language :: Python
Classifier: Programming Language :: Python :: 2
Classifier: Programming Language :: Python :: 2.7
Classifier: Programming Language :: Python :: 3
Classifier: Programming Language :: Python :: 3.4
